notion_as_db/__init__.py
notion_as_db/configured_notion.py
notion_as_db-0.0.2.dist-info/LICENSE
notion_as_db-0.0.2.dist-info/METADATA
notion_as_db-0.0.2.dist-info/WHEEL
notion_as_db-0.0.2.dist-info/top_level.txt
notion_as_db-0.0.2.dist-info/RECORD
